[
    {
        "agency": "Main",
        "code": "EN-01",
        "category": "Engagement",
        "task": "Join WOG Data Science Workplace group",
        "points": {
            "datadex_2023": 500
        },
        "limit": 1,
        "items": [
            "ear_003_elfear1",
            "ear_003_elfear2",
            "ear_003_elfear3",
            "ear_003_elfear4"
        ]
    },
    {
        "agency": "Main",
        "code": "EN-02",
        "category": "Engagement",
        "task": "Subscribe to DSC Spark mailing list",
        "points": {
            "datadex_2023": 500
        },
        "limit": 1,
        "items": [
            "eye_004_shades_black",
            "eye_004_shades_blue",
            "eye_004_shades_green",
            "eye_004_shades_orange",
            "eye_004_shades_pink",
            "eye_004_shades_purple",
            "eye_004_shades_red",
            "eye_004_shades_yellow"
        ]
    },
    {
        "agency": "Main",
        "code": "EN-03",
        "category": "Engagement",
        "task": "Contribute Quick-Fire video",
        "points": {
            "datadex_2023": 7000
        },
        "limit": 3,
        "items": [
            "hand_024_bomb"
        ]
    },
    {
        "agency": "Main",
        "code": "EN-04",
        "category": "Engagement",
        "task": "Complete Datadex Diaries 2022",
        "points": {
            "datadex_2023": 10000
        },
        "limit": 1,
        "items": [
            "hand_900_pokedex"
        ]
    },
    {
        "agency": "Main",
        "code": "EN-05",
        "category": "Engagement",
        "task": "Organising Committee of Datadex X 2023",
        "points": {
            "datadex_2023": 10000
        },
        "limit": 1,
        "items": [
            "addon_012_neonvest"
        ]
    },
    {
        "agency": "Main",
        "code": "EN-06",
        "category": "Engagement",
        "task": "Complete Datadex Diaries 2023",
        "points": {
            "datadex_2023": 5000
        },
        "limit": 1,
        "items": [
            "hand_070_pokeball"
        ]
    },
    {
        "agency": "Main",
        "code": "TR-01",
        "category": "Training",
        "task": "Attend Workshop (test drive, upskilling initiative etc)",
        "points": {
            "datadex_2023": 2500
        },
        "limit": 3,
        "items": [
            "hand_033_balloon_black",
            "hand_033_balloon_blue",
            "hand_033_balloon_green",
            "hand_033_balloon_orange",
            "hand_033_balloon_pink",
            "hand_033_balloon_purple",
            "hand_033_balloon_red",
            "hand_033_balloon_white",
            "hand_033_balloon_yellow"
        ]
    },
    {
        "agency": "Main",
        "code": "TR-02",
        "category": "Training",
        "task": "Attend Masterclass",
        "points": {
            "datadex_2023": 2500
        },
        "limit": 3,
        "items": [
            "hand_073_lighsabre_blue",
            "hand_073_lighsabre_green",
            "hand_073_lighsabre_purple",
            "hand_073_lighsabre_red",
            "hand_073_lighsabre_yellow"
        ]
    },
    {
        "agency": "Main",
        "code": "TR-03",
        "category": "Training",
        "task": "Complete Data Literacy ePrimer Modules",
        "points": {
            "datadex_2023": 5000
        },
        "limit": 1,
        "items": [
            "pet_067_datamascot",
            "pet_068_eprimerguy",
            "pet_069_eprimerboss",
            "pet_070_eprimerbusinessanalyst",
            "pet_071_eprimerprojectlead",
            "pet_072_eprimerdatascientist"
        ]
    },
    {
        "agency": "Main",
        "code": "TR-04",
        "category": "Training",
        "task": "Read and Feedback on Prompt Engineering Playbook",
        "points": {
            "datadex_2023": 2000
        },
        "limit": 1,
        "items": [
            "hand_046_blackboard"
        ]
    },
    {
        "agency": "Main",
        "code": "DSAID-01",
        "category": "DSAID",
        "task": "Attend GovTech's DSAID Roadshow",
        "points": {
            "datadex_2023": 1000
        },
        "limit": 1,
        "items": [
            "hand_083_racingflag"
        ]
    },
    {
        "agency": "Main",
        "code": "DSAID-02",
        "category": "DSAID",
        "task": "Complete GovTech's DSAID Roadshow feedback form",
        "points": {
            "datadex_2023": 1000
        },
        "limit": 1,
        "items": [
            "pet_073_toycar_black",
            "pet_073_toycar_blue",
            "pet_073_toycar_green",
            "pet_073_toycar_red",
            "pet_073_toycar_white"
        ]
    },
    {
        "agency": "Main",
        "code": "DSC-01",
        "category": "DSC",
        "task": "Register for Data Science Connect #25",
        "points": {
            "datadex_2023": 500
        },
        "limit": 1,
        "items": [
            "body_009_labcoat",
            "leg_004_jeans_black",
            "leg_004_jeans_blue",
            "leg_004_jeans_white"
        ]
    },
    {
        "agency": "Main",
        "code": "DSC-02",
        "category": "DSC",
        "task": "Attend Data Science Connect #25",
        "points": {
            "datadex_2023": 1000
        },
        "limit": 1,
        "items": [
            "eye_011_goggles_blue",
            "eye_011_goggles_green",
            "eye_011_goggles_orange",
            "eye_011_goggles_pink",
            "eye_011_goggles_purple",
            "eye_011_goggles_red",
            "eye_011_goggles_yellow",
            "hand_034_testtube_blue",
            "hand_034_testtube_green",
            "hand_034_testtube_red"
        ]
    },
    {
        "agency": "Main",
        "code": "DSC-03",
        "category": "DSC",
        "task": "Complete Data Science Connect feedback form",
        "points": {
            "datadex_2023": 1000
        },
        "limit": 1,
        "items": [
            "background_005_lab"
        ]
    },
    {
        "agency": "Main",
        "code": "DSC-04",
        "category": "DSC",
        "task": "Register for STACKx: Data & AI",
        "points": {
            "datadex_2023": 500
        },
        "limit": 1,
        "items": [
            "body_024_overalls_darkblack",
            "body_024_overalls_darkblue",
            "body_024_overalls_darkgreen",
            "body_024_overalls_darkorange",
            "body_024_overalls_darkpink",
            "body_024_overalls_darkpurple",
            "body_024_overalls_darkred",
            "body_024_overalls_darkyellow"
        ]
    },
    {
        "agency": "Main",
        "code": "DSC-05",
        "category": "DSC",
        "task": "Attend STACKx: Data & AI",
        "points": {
            "datadex_2023": 2000
        },
        "limit": 1,
        "items": [
            "pet_077_extraterrestrial"
        ]
    },
    {
        "agency": "Main",
        "code": "DSC-06",
        "category": "DSC",
        "task": "Complete STACKx: Data & AI feedback form",
        "points": {
            "datadex_2023": 1000
        },
        "limit": 1,
        "items": [
            "background_017_bigmoon"
        ]
    },
    {
        "agency": "Main",
        "code": "DSC-07",
        "category": "DSC",
        "task": "Register for Data Science Connect #26 x DAT2023 Finale",
        "points": {
            "datadex_2023": 500
        },
        "limit": 1,
        "items": [
            "back_006_butterfly_blue",
            "back_006_butterfly_orange",
            "back_006_butterfly_red",
            "background_022_hokusai",
            "body_041_dscbodysuit",
            "eye_006_cyclops",
            "eye_006_cyclops_black",
            "eye_006_cyclops_blue",
            "eye_006_cyclops_green",
            "eye_006_cyclops_orange",
            "eye_006_cyclops_white",
            "eye_006_cyclops_yellow",
            "hair_029_cyber_blue_andro",
            "hair_029_cyber_blue_long",
            "hair_029_cyber_blue_short",
            "hand_088_vineflag_green",
            "hand_088_vineflag_red",
            "head_040_butterflyhairband_green",
            "head_040_butterflyhairband_orange",
            "head_040_butterflyhairband_pink",
            "head_040_butterflyhairband_purple",
            "head_040_butterflyhairband_red",
            "head_040_butterflyhairband_yellow",
            "pet_093_caterpillar_bnw",
            "pet_093_caterpillar_brown",
            "pet_093_caterpillar_green",
            "pet_093_caterpillar_orange",
            "pet_093_caterpillar_pink",
            "pet_093_caterpillar_yellow"
        ]
    },
    {
        "agency": "Main",
        "code": "DAT-01",
        "category": "DAT",
        "task": "Register for Data VIZard 2023",
        "points": {
            "datadex_2023": 500
        },
        "limit": 1,
        "items": [
            "feet_002_largeshoes_black",
            "feet_002_largeshoes_blue",
            "feet_002_largeshoes_green",
            "feet_002_largeshoes_orange",
            "feet_002_largeshoes_pink",
            "feet_002_largeshoes_purple",
            "feet_002_largeshoes_red",
            "feet_002_largeshoes_white",
            "feet_002_largeshoes_yellow",
            "head_018_wizardhat_black",
            "head_018_wizardhat_blue",
            "head_018_wizardhat_green",
            "head_018_wizardhat_orange",
            "head_018_wizardhat_pink",
            "head_018_wizardhat_purple",
            "head_018_wizardhat_red",
            "head_018_wizardhat_white",
            "head_018_wizardhat_yellow"
        ]
    },
    {
        "agency": "Main",
        "code": "DAT-02",
        "category": "DAT",
        "task": "Submit Entry for Data VIZard 2023",
        "points": {
            "datadex_2023": 8000
        },
        "limit": 1,
        "items": [
            "body_021_wizard_black",
            "body_021_wizard_blue",
            "body_021_wizard_green",
            "body_021_wizard_orange",
            "body_021_wizard_pink",
            "body_021_wizard_purple",
            "body_021_wizard_red",
            "body_021_wizard_white",
            "body_021_wizard_yellow",
            "hand_027_wand_blue",
            "hand_027_wand_green",
            "hand_027_wand_orange",
            "hand_027_wand_pink",
            "hand_027_wand_purple",
            "hand_027_wand_red",
            "hand_027_wand_yellow"
        ]
    },
    {
        "agency": "Main",
        "code": "DAT-03",
        "category": "DAT",
        "task": "Achieve Top 10 Teams in Data VIZard",
        "points": {
            "datadex_2023": 3000
        },
        "limit": 1,
        "items": [
            "body_037_specialwizard",
            "hand_077_specialwand",
            "head_034_specialwizardhat"
        ]
    },
    {
        "agency": "Main",
        "code": "DAT-04",
        "category": "DAT",
        "task": "Achieve Top 5 Teams in Data VIZard",
        "points": {
            "datadex_2023": 5000
        },
        "limit": 1,
        "items": [
            "background_018_dungeon",
            "pet_078_eyetower"
        ]
    },
    {
        "agency": "Main",
        "code": "DAT-08",
        "category": "DAT",
        "task": "Register for Launch of Data Arcade Tournament 2023",
        "points": {
            "datadex_2023": 500
        },
        "limit": 1,
        "items": [
            "body_003_gymtop_black",
            "body_003_gymtop_blue",
            "body_003_gymtop_green",
            "body_003_gymtop_orange",
            "body_003_gymtop_pink",
            "body_003_gymtop_purple",
            "body_003_gymtop_red",
            "body_003_gymtop_white",
            "body_003_gymtop_yellow",
            "body_008_shirt_black",
            "body_008_shirt_blue",
            "body_008_shirt_green",
            "body_008_shirt_orange",
            "body_008_shirt_pink",
            "body_008_shirt_purple",
            "body_008_shirt_red"
        ]
    },
    {
        "agency": "Main",
        "code": "DAT-09",
        "category": "DAT",
        "task": "Attend Launch of Data Arcade Tournament 2023",
        "points": {
            "datadex_2023": 1000
        },
        "limit": 1,
        "items": [
            "pet_049_piggybank_gold"
        ]
    },
    {
        "agency": "Main",
        "code": "DAT-10",
        "category": "DAT",
        "task": "Complete Launch of Data Arcade Tournament 2023 Feedback Form",
        "points": {
            "datadex_2023": 1000
        },
        "limit": 1,
        "items": [
            "background_015_homegym"
        ]
    },
    {
        "agency": "Main",
        "code": "DAT-11",
        "category": "DAT",
        "task": "Register for Prompt Royale 2023",
        "points": {
            "datadex_2023": 500
        },
        "limit": 1,
        "items": [
            "feet_003_longshoes_black",
            "feet_003_longshoes_blue",
            "feet_003_longshoes_green",
            "feet_003_longshoes_orange",
            "feet_003_longshoes_pink",
            "feet_003_longshoes_purple",
            "feet_003_longshoes_red",
            "feet_003_longshoes_white",
            "feet_003_longshoes_yellow",
            "head_023_visor_black",
            "head_023_visor_blue",
            "head_023_visor_green",
            "head_023_visor_orange",
            "head_023_visor_pink",
            "head_023_visor_purple",
            "head_023_visor_red",
            "head_023_visor_yellow"
        ]
    },
    {
        "agency": "Main",
        "code": "DAT-12",
        "category": "DAT",
        "task": "Submit Entry for Prompt Royale 2023",
        "points": {
            "datadex_2023": 6000
        },
        "limit": 2,
        "items": [
            "body_013_designerteepython",
            "hand_050_shovel"
        ]
    },
    {
        "agency": "Main",
        "code": "DAT-13",
        "category": "DAT",
        "task": "Achieve Top 9 for Prompt Royale 2023",
        "points": {
            "datadex_2023": 1000
        },
        "limit": 1,
        "items": [
            "background_010_mountain",
            "pet_013_rabbit_white"
        ]
    },
    {
        "agency": "Main",
        "code": "DATX-01",
        "category": "DAT X",
        "task": "Register for ImpactiVIZ 2023",
        "points": {
            "datadex_2023": 500
        },
        "limit": 1,
        "items": [
            "feet_005_boots_black",
            "feet_005_boots_blue",
            "feet_005_boots_green",
            "feet_005_boots_orange",
            "feet_005_boots_pink",
            "feet_005_boots_purple",
            "feet_005_boots_red",
            "feet_005_boots_white",
            "feet_005_boots_yellow",
            "head_022_construction_white",
            "head_022_construction_yellow"
        ]
    },
    {
        "agency": "Main",
        "code": "DATX-02",
        "category": "DAT X",
        "task": "Submit Entry for ImpactiVIZ 2023",
        "points": {
            "datadex_2023": 8000
        },
        "limit": 1,
        "items": [
            "hand_020_pickaxe"
        ]
    },
    {
        "agency": "Main",
        "code": "DATX-06",
        "category": "DAT X",
        "task": "Achieve Top 3 DATx Teams in Agency",
        "points": {
            "datadex_2023": 2000
        },
        "limit": 1,
        "items": [
            "face_011_scareye"
        ]
    },
    {
        "agency": "Main",
        "code": "DATX-03",
        "category": "DAT X",
        "task": "Achieve Top DATx Team in Agency",
        "points": {
            "datadex_2023": 3000
        },
        "limit": 1,
        "items": [
            "pet_076_datgold"
        ]
    },
    {
        "agency": "Main",
        "code": "DATX-04",
        "category": "DAT X",
        "task": "Achieve Top 5 Teams in ImpactiVIZ 2023",
        "points": {
            "datadex_2023": 5000
        },
        "limit": 1,
        "items": [
            "background_012_cave"
        ]
    },
    {
        "agency": "Main",
        "code": "DATX-05",
        "category": "DAT X",
        "task": "Organising Committee and Judges Panel of ImpactiVIZ 2023",
        "points": {
            "datadex_2023": 10000
        },
        "limit": 1,
        "items": [
            "head_035_specialconstruction"
        ]
    },
    {
        "agency": "Main",
        "code": "DCBC-01",
        "category": "DC Bootcamp",
        "task": "Register for DC Bootcamp 2023",
        "points": {
            "datadex_2023": 500
        },
        "limit": 1,
        "items": [
            "addon_005_gloves_black",
            "body_017_minion",
            "eye_008_minion",
            "leg_014_minion"
        ]
    },
    {
        "agency": "Main",
        "code": "DCBC-02",
        "category": "DC Bootcamp",
        "task": "Graduate from DC Bootcamp (Certified) 2023",
        "points": {
            "datadex_2023": 8000
        },
        "limit": 1,
        "items": [
            "body_023_graduation_blue",
            "head_021_graduation_blue"
        ]
    },
    {
        "agency": "Main",
        "code": "DCBC-03",
        "category": "DC Bootcamp",
        "task": "Graduate from DC Bootcamp X",
        "points": {
            "datadex_2023": 9500
        },
        "limit": 1,
        "items": [
            "body_023_graduation_black",
            "head_021_graduation_black"
        ]
    },
    {
        "agency": "Main",
        "code": "DCBC-04",
        "category": "DC Bootcamp",
        "task": "Volunteer as DC Bootcamp X Trainer (weekly basis)",
        "points": {
            "datadex_2023": 1000
        },
        "limit": 25,
        "items": [
            "body_005_jacket_black",
            "hand_084_loudhailer",
            "leg_017_overalls_darkblack",
            "neck_001_scarf_black",
            "pet_019_minion"
        ]
    },
    {
        "agency": "Main",
        "code": "DCBC-05",
        "category": "DC Bootcamp",
        "task": "Volunteer as DC Bootcamp X Coordinator",
        "points": {
            "datadex_2023": 10000
        },
        "limit": 1,
        "items": [
            "body_007_longdress_blue",
            "eye_002_bigspecs_blue",
            "hair_022_dye_orange",
            "hand_045_lasergun",
            "neck_001_scarf_red"
        ]
    },
    {
        "agency": "Main",
        "code": "DCBC-06",
        "category": "DC Bootcamp",
        "task": "Active contribution to DC Bootcamp community (segment basis)",
        "points": {
            "datadex_2023": 500
        },
        "limit": 4,
        "items": [
            "hand_052_laptopmini"
        ]
    },
    {
        "agency": "Main",
        "code": "DCBC-07",
        "category": "DC Bootcamp",
        "task": "Complete Section 1 - Python: Fundamentals",
        "points": {
            "datadex_2023": 0
        },
        "limit": 1,
        "items": [
            "pet_001_python"
        ]
    },
    {
        "agency": "Main",
        "code": "DCBC-08",
        "category": "DC Bootcamp",
        "task": "Complete Section 2 - Python: Data Wrangling",
        "points": {
            "datadex_2023": 0
        },
        "limit": 1,
        "items": [
            "pet_002_panda"
        ]
    },
    {
        "agency": "Main",
        "code": "DCBC-09",
        "category": "DC Bootcamp",
        "task": "Complete Section 3 - Machine Learning",
        "points": {
            "datadex_2023": 0
        },
        "limit": 1,
        "items": [
            "pet_003_robot"
        ]
    },
    {
        "agency": "Main",
        "code": "DCBC-10",
        "category": "DC Bootcamp",
        "task": "Complete Section 4 - Data Visualisation (Tableau, PowerBI, QlikSense)",
        "points": {
            "datadex_2023": 0
        },
        "limit": 1,
        "items": [
            "pet_004_octopus"
        ]
    },
    {
        "agency": "Main",
        "code": "LP-01",
        "category": "Ideathon",
        "task": "Sign in to Launchpad",
        "points": {
            "datadex_2023": 500
        },
        "limit": 1,
        "items": [
            "body_011_council",
            "hair_003_f4",
            "leg_016_astronaut_blue",
            "leg_016_astronaut_orange"
        ]
    },
    {
        "agency": "Main",
        "code": "LP-02",
        "category": "Ideathon",
        "task": "Vote for an Ideathon entry",
        "points": {
            "datadex_2023": 500
        },
        "limit": 3,
        "items": [
            "head_020_astronaut_blue",
            "head_020_astronaut_orange"
        ]
    },
    {
        "agency": "Main",
        "code": "LP-03",
        "category": "Ideathon",
        "task": "Submit an entry for Ideathon",
        "points": {
            "datadex_2023": 2000
        },
        "limit": 5,
        "items": [
            "hand_029_flag_black",
            "hand_029_flag_blue",
            "hand_029_flag_green",
            "hand_029_flag_orange",
            "hand_029_flag_pink",
            "hand_029_flag_purple",
            "hand_029_flag_red",
            "hand_029_flag_white",
            "hand_029_flag_yellow"
        ]
    },
    {
        "agency": "Main",
        "code": "ADHOC-01",
        "category": "Adhoc",
        "task": "Achieve Top 3 in Prompt Challenge for Data Science Connect #25",
        "points": {
            "datadex_2023": 1500
        },
        "limit": 1,
        "items": [
            "hand_053_linechart"
        ]
    },
    {
        "agency": "Main",
        "code": "ADHOC-02",
        "category": "Adhoc",
        "task": "Submit a #ootDSC25 entry on Workplace",
        "points": {
            "datadex_2023": 500
        },
        "limit": 1,
        "items": [
            "hand_080_katana"
        ]
    },
    {
        "agency": "Main",
        "code": "ADHOC-03",
        "category": "Adhoc",
        "task": "Achieve top 10 #ootDSC25 entries on Workplace",
        "points": {
            "datadex_2023": 1500
        },
        "limit": 1,
        "items": [
            "head_011_centurion"
        ]
    },
    {
        "agency": "Main",
        "code": "ADHOC-04",
        "category": "Adhoc",
        "task": "Login to LaunchPad (1 Aug to 14 Aug)",
        "points": {
            "datadex_2023": 500
        },
        "limit": 1,
        "items": [
            "background_020_ndp01",
            "pet_040_otter"
        ]
    },
    {
        "agency": "Main",
        "code": "ADHOC-05",
        "category": "Adhoc",
        "task": "Login to LaunchPad (15 Aug to 31 Aug)",
        "points": {
            "datadex_2023": 500
        },
        "limit": 1,
        "items": [
            "background_021_ndp02",
            "pet_082_dragonplayground"
        ]
    },
    {
        "agency": "Main",
        "code": "ADHOC-06",
        "category": "Adhoc",
        "task": "Upload a post-workshop feedback on Workplace",
        "points": {
            "datadex_2023": 1000
        },
        "limit": 1,
        "items": [
            "pet_056_rocketship_orange",
            "pet_056_rocketship_pink",
            "pet_056_rocketship_purple"
        ]
    },
    {
        "agency": "Main",
        "code": "ADHOC-07",
        "category": "Adhoc",
        "task": "Upload a post-workshop image on Workplace",
        "points": {
            "datadex_2023": 1000
        },
        "limit": 1,
        "items": [
            "pet_088_paintingvangough"
        ]
    },
    {
        "agency": "Main",
        "code": "DALIM-01",
        "category": "Data & AI Literacy Month",
        "task": "Complete all 5 Data Literacy ePrimer Modules (new AI additions)",
        "points": {
            "datadex_2023": 7500
        },
        "limit": 1,
        "items": [
            "addon_004_bigjacket_pink",
            "addon_004_bigjacket_purple",
            "addon_004_bigjacket_red"
        ]
    },
    {
        "agency": "Main",
        "code": "DALIM-02",
        "category": "Data & AI Literacy Month",
        "task": "Attend an eligible DALIM event (up to 3 counts)",
        "points": {
            "datadex_2023": 2000
        },
        "limit": 3,
        "items": [
            "back_003_cape_orange",
            "back_003_cape_pink",
            "back_003_cape_purple",
            "back_003_cape_red"
        ]
    },
    {
        "agency": "Main",
        "code": "DALIM-03",
        "category": "Data & AI Literacy Month",
        "task": "Complete one eligible DALIM course",
        "points": {
            "datadex_2023": 2000
        },
        "limit": 1,
        "items": [
            "body_035_armour_pink",
            "body_035_armour_purple",
            "body_035_armour_red"
        ]
    },
    {
        "agency": "Main",
        "code": "DALIM-04",
        "category": "Data & AI Literacy Month",
        "task": "Participate in Pledge Campaign (like and comment)",
        "points": {
            "datadex_2023": 1000
        },
        "limit": 1,
        "items": [
            "eye_002_bigspecs_purple",
            "eye_002_bigspecs_red"
        ]
    },
    {
        "agency": "Main",
        "code": "DALIM-05",
        "category": "Data & AI Literacy Month",
        "task": "Like a Data & AI Podcast post on Workplace",
        "points": {
            "datadex_2023": 500
        },
        "limit": 1,
        "items": [
            "hand_071_macbook"
        ]
    },
    {
        "agency": "MOM",
        "code": "DTDXMOM-01",
        "category": "MOM Data Community",
        "task": "Organising Committee of MOM DataBuds (1-year term).",
        "points": {
            "datadex_2023": 3000
        },
        "limit": 1,
        "items": [
            "pet_079_locker"
        ]
    },
    {
        "agency": "MOM",
        "code": "DTDXMOM-02",
        "category": "MOM Data Community",
        "task": "Volunteer to host sharing, training, hackathon on data analytics topic. E.g. MOM DataBuds session, MOM Data Lab workshop. Duration of session must be more than 1-hour (inclusive of activities); content creation can be co-shared up to 2 pax. 2000 points will be awarded per session & pax.",
        "points": {
            "datadex_2023": 2000
        },
        "limit": 2,
        "items": [
            "addon_004_bigjacket_blue"
        ]
    },
    {
        "agency": "MOM",
        "code": "DTDXMOM-03",
        "category": "MOM Data Community",
        "task": "Attend sharing session or training session on data analytics topic organised by MOM. E.g. MOM DataBuds sessions, MOM Data Lab workshop, MOM Tableau Brown Bag sessions. To validate participation, participant must complete feedback form for the initiative. 1000 points will be awarded per session.",
        "points": {
            "datadex_2023": 1000
        },
        "limit": 5,
        "items": [
            "hand_064_calculator"
        ]
    },
    {
        "agency": "MOM",
        "code": "DTDXMOM-04",
        "category": "MOM Data Community",
        "task": "Active Contributor in MOM Data Community MS Team - Contribute an article read or video watched on data analytics related topics (include 1-2 lines of key takeways in the post) in \"Bytes of Knowledge\" channel or address the question/enquiry posted in \"Ask-Me-Anything\" channel each month (from Feb to Oct). 500 points will be awarded per post/completed action, limit to once per month.",
        "points": {
            "datadex_2023": 500
        },
        "limit": 2,
        "items": [
            "hand_048_measuringtape"
        ]
    },
    {
        "agency": "MOM",
        "code": "DTDXMOM-05",
        "category": "MOM Data Community",
        "task": "Attend MOM DataViz Day 2023. To validate participation, participant must complete feedback form for the initiative.",
        "points": {
            "datadex_2023": 1500
        },
        "limit": 1,
        "items": [
            "addon_003_handcuffs"
        ]
    },
    {
        "agency": "MOM",
        "code": "DTDXMOM-06",
        "category": "MOM Data Community",
        "task": "Submit entry for Data Tournament organised by MOM e.g. 'MOMers Finding Insights 2023'",
        "points": {
            "datadex_2023": 1500
        },
        "limit": 1,
        "items": [
            "head_022_construction_white"
        ]
    },
    {
        "agency": "MOM",
        "code": "DTDXMOM-07",
        "category": "Tableau Server",
        "task": "Publish a dashboard on MOM Tableau Server with at least 10 unique viewers. 1000 point will be awarded per published dashboard.",
        "points": {
            "datadex_2023": 1000
        },
        "limit": 2,
        "items": [
            "hand_085_walkietalkie"
        ]
    },
    {
        "agency": "MOM",
        "code": "DTDXMOM-08",
        "category": "Tableau Server",
        "task": "Complete Tableau tutorial (inclusive of homework) organised by MOM. 500 points will be awarded per tutorial. Contact person - Ho Wee Peng.",
        "points": {
            "datadex_2023": 500
        },
        "limit": 2,
        "items": [
            "head_038_headphoneswithmic_blue",
            "head_038_headphoneswithmic_green",
            "head_038_headphoneswithmic_orange",
            "head_038_headphoneswithmic_pink",
            "head_038_headphoneswithmic_purple",
            "head_038_headphoneswithmic_red",
            "head_038_headphoneswithmic_yellow"
        ]
    },
    {
        "agency": "MOM",
        "code": "DTDXMOM-09",
        "category": "Adhoc",
        "task": "Participate in Tableau Blueprint Assessment",
        "points": {
            "datadex_2023": 1000
        },
        "limit": 1,
        "items": [
            "body_040_designerteecross"
        ]
    },
    {
        "agency": "HDB",
        "code": "DTDXHDB-01",
        "category": "DATxHDB Sharing",
        "task": "Be part of the organising committee of DATxHDB Sharing",
        "points": {
            "datadex_2023": 1500
        },
        "limit": 1,
        "items": [
            "addon_002_slingbag_green"
        ]
    },
    {
        "agency": "HDB",
        "code": "DTDXHDB-02",
        "category": "DATxHDB Sharing",
        "task": "Attend DATxHDB Sharing",
        "points": {
            "datadex_2023": 500
        },
        "limit": 1,
        "items": [
            "body_035_armour_orange"
        ]
    },
    {
        "agency": "HDB",
        "code": "DTDXHDB-03",
        "category": "DATxHDB Sharing",
        "task": "Submit feedback form for DATxHDB Sharing",
        "points": {
            "datadex_2023": 500
        },
        "limit": 1,
        "items": [
            "hand_041_umbrella_green"
        ]
    },
    {
        "agency": "HDB",
        "code": "DTDXHDB-04",
        "category": "DATxHDB Sharing",
        "task": "Present about your DATxHDB 2022 projects during DATxHDB Sharing",
        "points": {
            "datadex_2023": 1000
        },
        "limit": 1,
        "items": [
            "body_008_shirt_yellow"
        ]
    },
    {
        "agency": "HDB",
        "code": "DTDXHDB-05",
        "category": "DSAI Roadshow",
        "task": "Be part of the organising committee of DSAI COE Roadshow",
        "points": {
            "datadex_2023": 1500
        },
        "limit": 1,
        "items": [
            "eye_002_bigspecs_green"
        ]
    },
    {
        "agency": "HDB",
        "code": "DTDXHDB-06",
        "category": "DSAI Roadshow",
        "task": "Attend DSAI COE Roadshow",
        "points": {
            "datadex_2023": 500
        },
        "limit": 1,
        "items": [
            "face_005_twirlymoustache_white"
        ]
    },
    {
        "agency": "HDB",
        "code": "DTDXHDB-07",
        "category": "DSAI Roadshow",
        "task": "Submit feedback form for DSAI COE Roadshow",
        "points": {
            "datadex_2023": 500
        },
        "limit": 1,
        "items": [
            "leg_017_overalls_darkgreen"
        ]
    },
    {
        "agency": "HDB",
        "code": "DTDXHDB-08",
        "category": "DSAI Roadshow",
        "task": "Lead and share about their DSAI projects during DSAI COE Roadshow",
        "points": {
            "datadex_2023": 1000
        },
        "limit": 1,
        "items": [
            "hair_015_hairband_yellow"
        ]
    },
    {
        "agency": "HDB",
        "code": "DTDXHDB-09",
        "category": "DS Huddle",
        "task": "Be part of the organising committee of HDB Data Science Huddle Q3 2023",
        "points": {
            "datadex_2023": 1500
        },
        "limit": 1,
        "items": [
            "hand_018_firetorch"
        ]
    },
    {
        "agency": "HDB",
        "code": "DTDXHDB-10",
        "category": "DS Huddle",
        "task": "Attend HDB Data Science Huddle Q3 2023",
        "points": {
            "datadex_2023": 500
        },
        "limit": 1,
        "items": [
            "hand_049_key_white"
        ]
    },
    {
        "agency": "HDB",
        "code": "DTDXHDB-11",
        "category": "DS Huddle",
        "task": "Host or present about subject matter for Data Science Huddle Q3 2023",
        "points": {
            "datadex_2023": 1000
        },
        "limit": 1,
        "items": [
            "head_016_farmerhat_white"
        ]
    },
    {
        "agency": "HDB",
        "code": "DTDXHDB-12",
        "category": "DS Huddle",
        "task": "Submit feedback form for HDB Data Science Huddle Q3 2023",
        "points": {
            "datadex_2023": 500
        },
        "limit": 1,
        "items": [
            "head_032_helmhornsup_blue"
        ]
    },
    {
        "agency": "HDB",
        "code": "DTDXHDB-13",
        "category": "Community Participation",
        "task": "Attend other sharing session on data science related topics organized by HDB. Participants must register and complete feedback form to qualify for the points.",
        "points": {
            "datadex_2023": 1000
        },
        "limit": 5,
        "items": [
            "hand_051_bucket_pink"
        ]
    },
    {
        "agency": "HDB",
        "code": "DTDXHDB-14",
        "category": "Community Participation",
        "task": "Be an active contributor to the HDB DSAI Community by contributing DSAI-related articles, newsletter, topics and/or key takeaways from HDB DSAI formal/informal events like DSAI COE Roadshow or internal Book Club sharing",
        "points": {
            "datadex_2023": 250
        },
        "limit": 8,
        "items": [
            "hair_017_curls"
        ]
    },
    {
        "agency": "HDB",
        "code": "DTDXHDB-15",
        "category": "Community Participation",
        "task": "Host or present about subject matter for internal Book Club Sharing",
        "points": {
            "datadex_2023": 500
        },
        "limit": 5,
        "items": [
            "face_013_healthmask_white"
        ]
    },
    {
        "agency": "IMDA",
        "code": "DTDXIMDA-01",
        "category": "Tableau",
        "task": "Attend Tableau Training (in-house training using VISTA)",
        "points": {
            "datadex_2023": 5000
        },
        "limit": 1,
        "items": [
            "addon_002_slingbag_black"
        ]
    },
    {
        "agency": "IMDA",
        "code": "DTDXIMDA-02",
        "category": "InnoJam",
        "task": "Participate in InnoJam (Officers learn how innovation ideas can be conceived and tested while building internal capabilities)",
        "points": {
            "datadex_2023": 5000
        },
        "limit": 1,
        "items": [
            "body_035_armour_blue"
        ]
    },
    {
        "agency": "IMDA",
        "code": "DTDXIMDA-03",
        "category": "Deepracer",
        "task": "Participate in Deepracer (Officers learn about machine learning)",
        "points": {
            "datadex_2023": 5000
        },
        "limit": 1,
        "items": [
            "hand_041_umbrella_black"
        ]
    },
    {
        "agency": "MOE",
        "code": "DTDXMOE-01",
        "category": "Basic Digital Literacy",
        "task": "Complete a Basic Digital Literacy Module in OPAL 2.0",
        "points": {
            "datadex_2023": 1000
        },
        "limit": 5,
        "items": [
            "addon_002_slingbag_blue"
        ]
    },
    {
        "agency": "MOE",
        "code": "DTDXMOE-02",
        "category": "Data Analytics PLC",
        "task": "Attend Data Analytics Professional Learning Community (DA PLC)",
        "points": {
            "datadex_2023": 1000
        },
        "limit": 2,
        "items": [
            "body_035_armour_green"
        ]
    },
    {
        "agency": "MOE",
        "code": "DTDXMOE-03",
        "category": "Data Analytics PLC",
        "task": "Complete feedback form for DA PLC",
        "points": {
            "datadex_2023": 500
        },
        "limit": 2,
        "items": [
            "hand_041_umbrella_blue"
        ]
    },
    {
        "agency": "MOE",
        "code": "DTDXMOE-04",
        "category": "Data Analytics PLC",
        "task": "Present or share a use case at DA PLC",
        "points": {
            "datadex_2023": 2000
        },
        "limit": 1,
        "items": [
            "body_008_shirt_white"
        ]
    },
    {
        "agency": "MOE",
        "code": "DTDXMOE-05",
        "category": "MOE Tableau Workshops",
        "task": "Attend Tableau Workshops organised by MOE for DATxMOE",
        "points": {
            "datadex_2023": 1000
        },
        "limit": 2,
        "items": [
            "eye_002_bigspecs_black"
        ]
    },
    {
        "agency": "MOE",
        "code": "DTDXMOE-06",
        "category": "MOE Tableau Workshops",
        "task": "Complete feedback form for Tableau Workshops organised by MOE",
        "points": {
            "datadex_2023": 500
        },
        "limit": 1,
        "items": [
            "face_005_twirlymoustache"
        ]
    },
    {
        "agency": "MOE",
        "code": "DTDXMOE-07",
        "category": "Data at your Fingertips",
        "task": "Answer a quiz attached to Data at your Fingertips",
        "points": {
            "datadex_2023": 1250
        },
        "limit": 1,
        "items": [
            "hair_015_hairband_white"
        ]
    },
    {
        "agency": "MOE",
        "code": "DTDXMOE-08",
        "category": "AI Series: The Journey of Data Explorer, C.P. Yoo",
        "task": "Answer a quiz attached to AI Series: The Journey of Data Explorer, C.P. Yoo",
        "points": {
            "datadex_2023": 1250
        },
        "limit": 1,
        "items": [
            "hand_017_handaxe"
        ]
    },
    {
        "agency": "MOE",
        "code": "DTDXMOE-09",
        "category": "e-Pedagogy: Using Data to Inform Teaching and Learning",
        "task": "Complete e-Pedagogy: Using Data to Inform Teaching and Learning in SLS (Schools only)",
        "points": {
            "datadex_2023": 5000
        },
        "limit": 1,
        "items": [
            "hand_049_key_black"
        ]
    },
    {
        "agency": "MOE",
        "code": "DTDXMOE-10",
        "category": "MOE Data Science Community",
        "task": "Join the Data Science Community in SG-Teams (HQ only)",
        "points": {
            "datadex_2023": 2000
        },
        "limit": 1,
        "items": [
            "head_016_farmerhat_red"
        ]
    },
    {
        "agency": "MOE",
        "code": "DTDXMOE-11",
        "category": "MOE Data Science Community",
        "task": "Post or comment to a post in the Data Science Community in SG-Teams (HQ only)",
        "points": {
            "datadex_2023": 1000
        },
        "limit": 1,
        "items": [
            "leg_017_overalls_darkblue"
        ]
    },
    {
        "agency": "MOE",
        "code": "DTDXMOE-12",
        "category": "MOE Data Science Community",
        "task": "React to a post/comment on the Data Science Community in SG-Teams (HQ only)",
        "points": {
            "datadex_2023": 500
        },
        "limit": 2,
        "items": [
            "head_032_helmhornsup_black"
        ]
    },
    {
        "agency": "MOE",
        "code": "DTDXMOE-13",
        "category": "Data Analytics Clinic",
        "task": "Attend Data Analytics Clinic (HQ only)",
        "points": {
            "datadex_2023": 1000
        },
        "limit": 1,
        "items": [
            "hand_051_bucket_orange"
        ]
    },
    {
        "agency": "MSF",
        "code": "DTDXMSF-01",
        "category": "CANVAS adoption",
        "task": "Request for a CANVAS account and login to explore CANVAS (Discovery Zone/Main)",
        "points": {
            "datadex_2023": 500
        },
        "limit": 1,
        "items": [
            "addon_002_slingbag_orange"
        ]
    },
    {
        "agency": "MSF",
        "code": "DTDXMSF-02",
        "category": "CANVAS adoption",
        "task": "Share your findings / thoughts via a screenshot post of your visualization (*all identifiable information and labels are to be removed) created on CANVAS on OneMSF Data, Strategy and Innovation channel - with hastag #DTDxMSF",
        "points": {
            "datadex_2023": 2000
        },
        "limit": 2,
        "items": [
            "addon_013_smalljacket_blue"
        ]
    },
    {
        "agency": "MSF",
        "code": "DTDXMSF-03",
        "category": "Data Community Exchange - Engagement",
        "task": "Attend Q2 Data Community Exchange (DCE)",
        "points": {
            "datadex_2023": 500
        },
        "limit": 1,
        "items": [
            "addon_016_apron_blue"
        ]
    },
    {
        "agency": "MSF",
        "code": "DTDXMSF-04",
        "category": "Data Community Exchange - Engagement",
        "task": "Join MSF-DGO's teams channel for the latest update on data-related matters",
        "points": {
            "datadex_2023": 500
        },
        "limit": 1,
        "items": [
            "eye_002_bigspecs_orange"
        ]
    },
    {
        "agency": "MSF",
        "code": "DTDXMSF-05",
        "category": "Upskilling Data Skills",
        "task": "Form a team and submit an entry for MSF's DATx",
        "points": {
            "datadex_2023": 4500
        },
        "limit": 1,
        "items": [
            "hand_022_bow"
        ]
    },
    {
        "agency": "MSF",
        "code": "DTDXMSF-06",
        "category": "Upskilling Data Skills",
        "task": "Achieve top 3 for MSF DATx",
        "points": {
            "datadex_2023": 4000
        },
        "limit": 1,
        "items": [
            "head_016_farmerhat_green"
        ]
    },
    {
        "agency": "MSF",
        "code": "DTDXMSF-07",
        "category": "Upskilling Data Skills",
        "task": "Attend MSF-DATx workshop or any data-related course",
        "points": {
            "datadex_2023": 1000
        },
        "limit": 2,
        "items": [
            "neck_006_trianglescarf_blue"
        ]
    },
    {
        "agency": "MSF",
        "code": "DTDXMSF-08",
        "category": "Upskilling Data Skills",
        "task": "Use a dashboard (CANVAS / PowerBI / Tableau) for visualization at any meeting within MSF",
        "points": {
            "datadex_2023": 2000
        },
        "limit": 2,
        "items": [
            "pet_056_rocketship_blue"
        ]
    },
    {
        "agency": "PUB",
        "code": "DTDXPUB-01",
        "category": "Training",
        "task": "Attend workshop (workshop/tutorials/masterclass etc; up to 5)",
        "points": {
            "datadex_2023": 1500
        },
        "limit": 5,
        "items": [
            "addon_002_slingbag_pink"
        ]
    },
    {
        "agency": "PUB",
        "code": "DTDXPUB-02",
        "category": "Training",
        "task": "Log in to Qlik Continuous Classroom (QCC)",
        "points": {
            "datadex_2023": 500
        },
        "limit": 1,
        "items": [
            "addon_013_smalljacket_green"
        ]
    },
    {
        "agency": "PUB",
        "code": "DTDXPUB-03",
        "category": "Training",
        "task": "Completion of QCC's modules (up to 3)",
        "points": {
            "datadex_2023": 500
        },
        "limit": 3,
        "items": [
            "addon_016_apron_green"
        ]
    },
    {
        "agency": "PUB",
        "code": "DTDXPUB-04",
        "category": "Training",
        "task": "Complete 2 quizzes on Data Classification and Data Loss Protection by watching the Data Management Videos on PUBTube",
        "points": {
            "datadex_2023": 500
        },
        "limit": 1,
        "items": [
            "eye_002_bigspecs_pink"
        ]
    },
    {
        "agency": "PUB",
        "code": "DTDXPUB-05",
        "category": "Data Exploitation",
        "task": "4th to 10th place from DATx PUB's internal judging",
        "points": {
            "datadex_2023": 2000
        },
        "limit": 1,
        "items": [
            "hand_023_longbow"
        ]
    },
    {
        "agency": "PUB",
        "code": "DTDXPUB-06",
        "category": "Data Exploitation",
        "task": "Submit department use case on Qlik Sense's dashboards",
        "points": {
            "datadex_2023": 500
        },
        "limit": 1,
        "items": [
            "head_016_farmerhat_blue"
        ]
    },
    {
        "agency": "PUB",
        "code": "DTDXPUB-07",
        "category": "Data Exploitation",
        "task": "Publish a dashboard in PUB Qlik Sense",
        "points": {
            "datadex_2023": 1000
        },
        "limit": 1,
        "items": [
            "neck_006_trianglescarf_green"
        ]
    },
    {
        "agency": "PUB",
        "code": "DTDXPUB-08",
        "category": "Data Governance",
        "task": "Submit latest data dictionary and data catalogue for systems",
        "points": {
            "datadex_2023": 500
        },
        "limit": 1,
        "items": [
            "pet_056_rocketship_green"
        ]
    },
    {
        "agency": "PUB",
        "code": "DTDXPUB-09",
        "category": "Engagement",
        "task": "Attend GetTogether Session for Data Analysts",
        "points": {
            "datadex_2023": 2000
        },
        "limit": 1,
        "items": [
            "head_039_capbackwards_blue"
        ]
    },
    {
        "agency": "PUB",
        "code": "DTDXPUB-10",
        "category": "Engagement",
        "task": "Attend as an audience at Agency's Internal Judging",
        "points": {
            "datadex_2023": 1500
        },
        "limit": 1,
        "items": [
            "head_033_helmhornsdown_green"
        ]
    },
    {
        "agency": "PUB",
        "code": "DTDXPUB-11",
        "category": "Engagement",
        "task": "Logging in to Data Catalogue via Data Portal or Data Analytics Platform (DAP)",
        "points": {
            "datadex_2023": 500
        },
        "limit": 1,
        "items": [
            "head_024_buckethat_purple"
        ]
    },
    {
        "agency": "PUB",
        "code": "DTDXPUB-12",
        "category": "Ideathon",
        "task": "Submit an idea for Data Science project",
        "points": {
            "datadex_2023": 500
        },
        "limit": 1,
        "items": [
            "hand_075_plumb_white"
        ]
    },
    {
        "agency": "PUB",
        "code": "DTDXPUB-13",
        "category": "Process Automation",
        "task": "Migrate manual reporting to Qlik Sense Nprinting",
        "points": {
            "datadex_2023": 1000
        },
        "limit": 1,
        "items": [
            "hand_051_bucket_yellow"
        ]
    },
    {
        "agency": "PUB",
        "code": "DTDXPUB-14",
        "category": "Adhoc",
        "task": "Complete survey on Data Analyst/Stewards",
        "points": {
            "datadex_2023": 500
        },
        "limit": 1,
        "items": [
            "eye_017_eyemask_blue"
        ]
    }
]